carveracontroller/ARIALUNI.ttf
carveracontroller/CNC.py
carveracontroller/Controller.py
carveracontroller/GcodeViewer.py
carveracontroller/Objloader.py
carveracontroller/USBStream.py
carveracontroller/Utils.py
carveracontroller/WIFIStream.py
carveracontroller/XMODEM.py
carveracontroller/__init__.py
carveracontroller/__main__.py
carveracontroller/__version__.py
carveracontroller/addons/pendant/__init__.py
carveracontroller/addons/pendant/pendant.py
carveracontroller/addons/pendant/whb04.py
carveracontroller/addons/probing/ProbingControls.kv
carveracontroller/addons/probing/ProbingControls.py
carveracontroller/addons/probing/ProbingPopup.kv
carveracontroller/addons/probing/ProbingPopup.py
carveracontroller/addons/probing/data/icons_1024x768/angle/probe_angle_arbitrary_negative.png
carveracontroller/addons/probing/data/icons_1024x768/angle/probe_angle_arbitrary_positive.png
carveracontroller/addons/probing/data/icons_1024x768/angle/probe_angle_x_above.png
carveracontroller/addons/probing/data/icons_1024x768/angle/probe_angle_x_below.png
carveracontroller/addons/probing/data/icons_1024x768/angle/probe_angle_y_left.png
carveracontroller/addons/probing/data/icons_1024x768/angle/probe_angle_y_right.png
carveracontroller/addons/probing/data/icons_1024x768/calibration/Calibrate_4th_Axis_Y.png
carveracontroller/addons/probing/data/icons_1024x768/calibration/Calibrate_4th_Axis_Y_TT.png
carveracontroller/addons/probing/data/icons_1024x768/calibration/Calibrate_4th_Axis_Z.png
carveracontroller/addons/probing/data/icons_1024x768/calibration/Calibrate_Anchor_1.png
carveracontroller/addons/probing/data/icons_1024x768/calibration/Calibrate_Anchor_2.png
carveracontroller/addons/probing/data/icons_1024x768/calibration/Calibrate_BoreX.png
carveracontroller/addons/probing/data/icons_1024x768/calibration/Calibrate_BoreY.png
carveracontroller/addons/probing/data/icons_1024x768/calibration/Calibrate_BossX.png
carvera_controller_community-2.0.0.dist-info/METADATA
carvera_controller_community-2.0.0.dist-info/WHEEL
carvera_controller_community-2.0.0.dist-info/licenses/LICENSE
carvera_controller_community-2.0.0.dist-info/licenses/NOTICE
carvera_controller_community-2.0.0.dist-info/RECORD
