Metadata-Version: 2.4
Name: carvera-controller-community
Version: 2.0.0
Summary: Community developed controller for the Carvera CNC
License: GPL-2.0
License-File: LICENSE
License-File: NOTICE
Author: Carvera-Community
Requires-Python: >=3.9,<3.14
Classifier: License :: OSI Approved :: GNU General Public License v2 (GPLv2)
Classifier: Programming Language :: Python :: 3
Classifier: Programming Language :: Python :: 3.9
Classifier: Programming Language :: Python :: 3.10
Classifier: Programming Language :: Python :: 3.11
Classifier: Programming Language :: Python :: 3.12
Classifier: Programming Language :: Python :: 3.13
Requires-Dist: Kivy (>=2.3.1,<3.0.0)
Requires-Dist: hid (>=1.0.7,<2.0.0)
Requires-Dist: pyquicklz (>=1.4.1,<2.0.0)
Requires-Dist: pyserial (>=3.5,<4.0)
